pinwheels-0.0.0.dist-info/METADATA
pinwheels-0.0.0.dist-info/WHEEL
pinwheels-0.0.0.dist-info/licenses/LICENSE
pinwheels/__init__.py
pinwheels-0.0.0.dist-info/RECORD
